setup.py
bigone/__init__.py
bigone/base.py
bigone/client.py
bigone/ratelimiter.py
bigone.egg-info/PKG-INFO
bigone.egg-info/SOURCES.txt
bigone.egg-info/dependency_links.txt
bigone.egg-info/requires.txt
bigone.egg-info/top_level.txt