Metadata-Version: 1.0
Name: bigone
Version: 0.1.1
Summary: Python SDK for Big.One (https://big.one)
Home-page: https://github.com/jeffkit/bigone-python/
Author: jeff kit
Author-email: jeffkit.info@gmail.com
License: UNKNOWN
Platform: UNKNOWN
